ysyai2/__init__.py
ysyai2/_nbdev.py
ysyai2/cache.py
ysyai2/dataanalytics_apiserver.py
ysyai2/html2pdf.py
ysyai2/utils.py
ysyai2/canvas/__init__.py
ysyai2/canvas/apidata.py
ysyai2/canvas/grade.py
ysyai2/canvas/myfeedback.py
ysyai2/canvas/proc.py
ysyai2/canvas/refresh.py
ysyai2-0.0.1.dist-info/LICENSE
ysyai2-0.0.1.dist-info/METADATA
ysyai2-0.0.1.dist-info/WHEEL
ysyai2-0.0.1.dist-info/entry_points.txt
ysyai2-0.0.1.dist-info/top_level.txt
ysyai2-0.0.1.dist-info/RECORD
