Metadata-Version: 2.1
Name: ysyai2
Version: 0.0.1
Summary: Data analytics library for Canvas
Home-page: https://github.com/jkabc123/ysyai2
Author: Peter Yang
Author-email: yang.piyi@gmail.com
License: Apache Software License 2.0
Keywords: Canvas
Platform: UNKNOWN
Classifier: Development Status :: 3 - Alpha
Classifier: Intended Audience :: Developers
Classifier: License :: OSI Approved :: Apache Software License
Classifier: Natural Language :: English
Classifier: Programming Language :: Python :: 3.6
Classifier: Programming Language :: Python :: 3.7
Classifier: Programming Language :: Python :: 3.8
Requires-Python: >=3.6
Requires-Dist: pandas
Requires-Dist: dataclasses
Requires-Dist: pyodbc
